qubic/__init__.py
qubic/abstract_runner.py
qubic/job_manager.py
qubic/job_rpc_server.py
qubic/pulse_factory.py
qubic/rpc_client.py
qubic/run.py
qubic/soc_rpc_server.py
qubic/state_disc.py
qubic/toolchain.py
qubic/pygsti/__init__.py
qubic/pygsti/job_manager.py
qubic/pygsti/simulation_managers.py
qubic/pygsti/transpiler.py
qubic/results/__init__.py
qubic/results/counts.py
qubic/results/primitives.py
qubic/results/tools.py
qubic/rfsoc/__init__.py
qubic/rfsoc/bram.py
qubic/rfsoc/hwconfig.py
qubic/rfsoc/pl_interface.py
qubic/rfsoc/sync_interface.py
qubic/rfsoc/bits/024756ff/bram.json
qubic/rfsoc/bits/024756ff/cfgregs.json
qubic/rfsoc/bits/024756ff/dspregs.json
qubic/rfsoc/bits/024756ff/psbd_20231018175357_024756ff.xsa
qubic/rfsoc/bits/024756ff/rfdc.json
qubic/rfsoc/bits/728789b0/cfgregs.json
qubic/rfsoc/bits/728789b0/dspregs.json
qubic/rfsoc/bits/728789b0/psbd_20230620181145_728789b0.xsa
qubic/rfsoc/bits/728789b0/rfdc.json
qubic/rfsoc/bits/81f773e5/bram.json
qubic/rfsoc/bits/81f773e5/cfgregs.json
qubic/rfsoc/bits/81f773e5/dspregs.json
qubic/rfsoc/bits/81f773e5/psbd_20230217164835_81f773e5.xsa
qubic/rfsoc/bits/81f773e5/rfdc.json
qubic/rfsoc/bits/d3aeea54/bram.json
qubic/rfsoc/bits/d3aeea54/cfgregs.json
qubic/rfsoc/bits/d3aeea54/dspregs.json
qubic/rfsoc/bits/d3aeea54/psbd_20230621124732_d3aeea54.xsa
qubic/rfsoc/bits/d3aeea54/rfdc.json
qubic/rfsoc/bits/f24f1615/bram.json
qubic/rfsoc/bits/f24f1615/cfgregs.json
qubic/rfsoc/bits/f24f1615/dspregs.json
qubic/rfsoc/bits/f24f1615/psbd_20230703155636_f24f1615.xsa
qubic/rfsoc/bits/f24f1615/rfdc.json
qubic/sim/__init__.py
qubic/sim/cocotb_drivers.py
qubic/sim/sim_interface.py
qubic/sim/tools.py
qubic/trueq/__init__.py
qubic/trueq/job_manager.py
qubic/trueq/transpiler.py
lbl_qubic-25.8.0.dist-info/METADATA
lbl_qubic-25.8.0.dist-info/WHEEL
lbl_qubic-25.8.0.dist-info/licenses/LICENSE
lbl_qubic-25.8.0.dist-info/RECORD
