Metadata-Version: 2.4
Name: lbl-qubic
Version: 25.8.0
License-File: LICENSE
Requires-Python: >=3.10
Requires-Dist: distproc~=25.8.0
Requires-Dist: ipdb
Requires-Dist: numpy~=2.2
Requires-Dist: qubitconfig~=25.5.0
Requires-Dist: scikit-learn
Requires-Dist: scipy
Requires-Dist: tqdm
